{
  "$schema": "../../../schemas/api.schema.json",
  "element": "image-map",
  "type": "web-component",
  "description": "map + map-area: Modern responsive image map with percentage coordinates",
  "attributes": [
    {
      "name": "x",
      "kind": "host-api",
      "purpose": "config"
    },
    {
      "name": "y",
      "kind": "host-api",
      "purpose": "config"
    },
    {
      "name": "width",
      "kind": "host-api",
      "purpose": "config"
    },
    {
      "name": "height",
      "kind": "host-api",
      "purpose": "config"
    },
    {
      "name": "cx",
      "kind": "host-api",
      "purpose": "config"
    },
    {
      "name": "cy",
      "kind": "host-api",
      "purpose": "config"
    },
    {
      "name": "r",
      "kind": "host-api",
      "purpose": "config"
    },
    {
      "name": "points",
      "kind": "host-api",
      "purpose": "config"
    },
    {
      "name": "shape",
      "kind": "host-api",
      "purpose": "config"
    },
    {
      "name": "coords",
      "kind": "host-api",
      "purpose": "config"
    },
    {
      "name": "label",
      "kind": "host-api",
      "purpose": "config"
    },
    {
      "name": "href",
      "kind": "native",
      "purpose": "config"
    },
    {
      "name": "target",
      "kind": "host-api",
      "purpose": "config"
    },
    {
      "name": "tooltip",
      "kind": "host-api",
      "purpose": "config"
    },
    {
      "name": "disabled",
      "kind": "native",
      "purpose": "config"
    },
    {
      "name": "src",
      "kind": "native",
      "purpose": "config"
    },
    {
      "name": "alt",
      "kind": "native",
      "purpose": "config"
    },
    {
      "name": "viewBox",
      "kind": "host-api",
      "purpose": "config"
    },
    {
      "name": "preserveAspectRatio",
      "kind": "host-api",
      "purpose": "config"
    },
    {
      "name": "role",
      "kind": "native",
      "purpose": "config"
    },
    {
      "name": "data-disabled",
      "kind": "data",
      "purpose": "config"
    },
    {
      "name": "data-hover",
      "kind": "data",
      "purpose": "config"
    }
  ],
  "events": [
    {
      "name": "image-map:area-enter"
    },
    {
      "name": "image-map:area-leave"
    },
    {
      "name": "image-map:area-activate"
    }
  ],
  "childAttributes": [],
  "structure": [],
  "htmlvalidate": {
    "flow": true,
    "permittedContent": [
      "@flow"
    ]
  }
}
