{
  "$schema": "../../../schemas/api.schema.json",
  "element": "work-item",
  "type": "web-component",
  "description": "General-purpose work unit card — tasks, bugs, chores, spikes, and features with slotted title, status, priority, assignee, and linked stories",
  "htmlvalidate": { "flow": true, "permittedContent": ["@flow"] },
  "attributes": [
    { "name": "item-id",   "kind": "host-api", "purpose": "config", "type": "string",  "description": "Unique work item identifier, auto-sets HTML id" },
    { "name": "type",      "kind": "host-api", "purpose": "config", "type": "string",  "description": "Item type: task | bug | chore | spike | feature" },
    { "name": "priority",  "kind": "host-api", "purpose": "config", "type": "string",  "description": "Priority: critical | high | medium | low" },
    { "name": "status",    "kind": "host-api", "purpose": "config", "type": "string",  "description": "Status: backlog | to-do | in-progress | review | done | blocked" },
    { "name": "estimate",  "kind": "host-api", "purpose": "config", "type": "string",  "description": "Effort estimate (points, hours, t-shirt size)" },
    { "name": "assignee",  "kind": "host-api", "purpose": "config", "type": "string",  "description": "Assignee name" },
    { "name": "story-ids", "kind": "host-api", "purpose": "config", "type": "string",  "description": "Comma-separated linked user-story IDs" },
    { "name": "detail",    "kind": "host-api", "purpose": "config", "type": "string",  "description": "Detail level: full | compact | minimal" },
    { "name": "compact",   "kind": "host-api", "purpose": "config", "type": "boolean", "description": "Alias for detail=compact" },
    { "name": "src",       "kind": "host-api", "purpose": "config", "type": "string",  "description": "URL to JSON data" }
  ],
  "slots": [
    { "name": "title",       "description": "Work item heading (e.g., <h3>)" },
    { "name": "description", "description": "Work item description (e.g., <p>)" },
    { "name": "checklist",   "description": "Checklist or subtasks (e.g., <ul>)" },
    { "name": "notes",       "description": "Additional notes (e.g., <p>)" }
  ],
  "events": [
    { "name": "work-item:ready",    "detail": "{ itemId, title, type, priority, status }", "description": "Fired after render" },
    { "name": "work-item:status",   "detail": "{ status, itemId }",                        "description": "Fired when status changes" },
    { "name": "work-item:priority", "detail": "{ priority, itemId }",                      "description": "Fired when priority changes" }
  ]
}
